named_arrays/__init__.py
named_arrays/_core.py
named_arrays/_core_array_functions.py
named_arrays/_named_array_functions.py
named_arrays/colorsynth.py
named_arrays/ndfilters.py
named_arrays/numexpr.py
named_arrays/optimize.py
named_arrays/plt.py
named_arrays/py.typed
named_arrays/random.py
named_arrays/regridding.py
named_arrays/transformations.py
named_arrays/_functions/__init__.py
named_arrays/_functions/function_array_functions.py
named_arrays/_functions/function_named_array_functions.py
named_arrays/_functions/functions.py
named_arrays/_functions/tests/__init__.py
named_arrays/_functions/tests/test_functions.py
named_arrays/_functions/tests/test_functions_vertices.py
named_arrays/_matrices/__init__.py
named_arrays/_matrices/matrices.py
named_arrays/_matrices/matrices_directional.py
named_arrays/_matrices/matrices_input_output.py
named_arrays/_matrices/matrices_positional.py
named_arrays/_matrices/matrices_spectral.py
named_arrays/_matrices/matrices_spectral_directional.py
named_arrays/_matrices/matrices_spectral_positional.py
named_arrays/_matrices/matrices_temporal.py
named_arrays/_matrices/matrices_temporal_positional.py
named_arrays/_matrices/matrices_temporal_spectral.py
named_arrays/_matrices/matrices_temporal_spectral_directional.py
named_arrays/_matrices/matrices_temporal_spectral_positional.py
named_arrays/_matrices/cartesian/__init__.py
named_arrays/_matrices/cartesian/matrices_cartesian.py
named_arrays/_matrices/cartesian/matrices_cartesian_2d.py
named_arrays/_matrices/cartesian/matrices_cartesian_3d.py
named_arrays/_matrices/cartesian/matrices_cartesian_nd.py
named_arrays/_matrices/cartesian/tests/__init__.py
named_arrays/_matrices/cartesian/tests/test_matrices_cartesian.py
named_arrays/_matrices/cartesian/tests/test_matrices_cartesian_2d.py
named_arrays/_matrices/tests/__init__.py
named_arrays/_matrices/tests/test_matrices.py
named_arrays/_scalars/__init__.py
named_arrays/_scalars/scalar_array_functions.py
named_arrays-0.27.0.dist-info/METADATA
named_arrays-0.27.0.dist-info/WHEEL
named_arrays-0.27.0.dist-info/top_level.txt
named_arrays-0.27.0.dist-info/RECORD
