Metadata-Version: 2.4
Name: named-arrays
Version: 0.27.0
Summary: Numpy arrays with labeled axes, similar to xarray but with support for uncertainties
Author-email: "Roy T. Smart" <roytsmart@gmail.com>, "Jacob D. Parker" <jacobdparker@gmail.com>
Project-URL: Homepage, https://github.com/sun-data/named-arrays
Project-URL: Documentation, https://named-arrays.readthedocs.io/en/latest
Classifier: Programming Language :: Python :: 3
Requires-Python: >=3.10
Requires-Dist: typing_extensions
Requires-Dist: numpy<2
Requires-Dist: numexpr
Requires-Dist: matplotlib
Requires-Dist: scipy
Requires-Dist: astropy
Requires-Dist: astroscrappy
Requires-Dist: ndfilters==0.3.1
Requires-Dist: colorsynth==0.1.5
Requires-Dist: regridding==0.2.0
Requires-Dist: xarray
Provides-Extra: test
Requires-Dist: pytest; extra == "test"
Requires-Dist: pytest-split; extra == "test"
Provides-Extra: doc
Requires-Dist: pytest; extra == "doc"
Requires-Dist: graphviz; extra == "doc"
Requires-Dist: Sphinx<8.2; extra == "doc"
Requires-Dist: sphinx-autodoc-typehints; extra == "doc"
Requires-Dist: sphinxcontrib-bibtex; extra == "doc"
Requires-Dist: pydata-sphinx-theme; extra == "doc"
Requires-Dist: ipykernel; extra == "doc"
Requires-Dist: jupyter-sphinx; extra == "doc"
Requires-Dist: nbsphinx; extra == "doc"
Requires-Dist: sphinx-codeautolink; extra == "doc"
Requires-Dist: sphinx-favicon; extra == "doc"
Requires-Dist: pooch; extra == "doc"
